{
	"version": "7",
	"dialect": "postgresql",
	"entries": [
		{
			"idx": 0,
			"version": "7",
			"when": 1761726909648,
			"tag": "0000_init",
			"breakpoints": true
		},
		{
			"idx": 1,
			"version": "7",
			"when": 1761726915301,
			"tag": "0001_enable_postgis_extension",
			"breakpoints": true
		},
		{
			"idx": 2,
			"version": "7",
			"when": 1762410420868,
			"tag": "0002_merge-all-migrations",
			"breakpoints": true
		},
		{
			"idx": 3,
			"version": "7",
			"when": 1762946187282,
			"tag": "0003_create-notification-table",
			"breakpoints": true
		}
	]
}
